{
    "response": "Shree Roopnarayan Ji Mandir is one of the oldest temple of india in rajsamand district located in sevantri(sewantri) village near charbhuja. for more info just say how to reach temple? or for more info download our officail app from playstore just by click below.",
    "expectUserResponse": true,
    "conversationToken": "EosDS2o5Wm...",
    "audioResponse": "//NExAAScH...",
    "ssmlMarkList": [],
    "debugInfo": {
        "sharedDebugInfoList": [],
        "conversationBuilderExecutionEventsList": []
    },
    "conversationBuilderDebugInfo": {
        "eventList": []
    },
    "visualResponse": {
        "visualElementsList": [
            {
                "displayText": {
                    "content": "Shree Roopnarayan Ji Mandir is one of the oldest temple of india in rajsamand district located in sevantri(sewantri) village near charbhuja. for more info just say how to reach temple? or for more info download our officail app from playstore just by click below."
                }
            },
            {
                "basicCard": {
                    "title": "Shree Roopnarayan ji Mandir",
                    "subtitle": "sevantri , Rajsamand.",
                    "formattedText": "download the app from below link to get more information.",
                    "image": {
                        "url": "https://upload.wikimedia.org/wikipedia/commons/5/53/Shreeroopnarayanjimandir.jpg",
                        "accessibilityText": "Shree Roopnarayan ji Mandir",
                        "height": 0,
                        "width": 0
                    },
                    "buttonsList": [
                        {
                            "title": "offical app link from playstore",
                            "openUrlAction": {
                                "url": "https://play.google.com/store/apps/details?id=shree.roopnarayanji.mandir&hl=en&gl=US",
                                "urlTypeHint": 0
                            }
                        }
                    ],
                    "imageDisplayOptions": 0
                }
            }
        ],
        "suggestionsList": [
            {
                "title": "about village"
            },
            {
                "title": "images"
            },
            {
                "title": "go back"
            }
        ],
        "agentLogoUrl": "https://lh3.googleusercontent.com/72b1NBzRfpov8zx-MAjzfgMBFsGr4Dj_fio_tIQYITKCSOoIei6PbXAYVCuw7ttCNDJOaSQvSBQA1A",
        "agentStyle": {
            "primaryColor": "",
            "fontFamily": "",
            "borderRadius": 0
        }
    },
    "clientError": 0,
    "is3pResponse": true,
    "clientOperationList": [
        {
            "operationType": 8,
            "showSuggestionsPayLoad": {
                "textsList": [
                    "about village",
                    "images",
                    "go back"
                ]
            }
        },
        {
            "operationType": 1,
            "micUpdatePayLoad": {
                "micMode": 1
            }
        }
    ],
    "projectName": "",
    "renderedHtml": "",
    "previewStartTimeMicros": "",
    "isEmptyResponse": false,
    "agentName": "Shri Roop narayan Ji Mandir",
    "servingModelOutdated": false,
    "request": "about temple?"
}