{
    "response": "Greetings!",
    "expectUserResponse": true,
    "conversationToken": "EosDS2o5Wm...",
    "audioResponse": "//NExAAQaJ...",
    "ssmlMarkList": [],
    "debugInfo": {
        "sharedDebugInfoList": [],
        "conversationBuilderExecutionEventsList": []
    },
    "conversationBuilderDebugInfo": {
        "eventList": []
    },
    "visualResponse": {
        "visualElementsList": [
            {
                "displayText": {
                    "content": "Greetings!"
                }
            }
        ],
        "suggestionsList": [],
        "agentLogoUrl": "https://lh3.googleusercontent.com/xe2W-wuxvuCLTr-VRfi588_gvDDYjOu1ET4z3WLd5PQ0KJFOKIlw3YQ9DVKFMUapxdsQ_p9T7ykLPg",
        "agentStyle": {
            "primaryColor": "",
            "fontFamily": "",
            "borderRadius": 0
        }
    },
    "clientError": 0,
    "is3pResponse": true,
    "clientOperationList": [
        {
            "operationType": 4,
            "startIndicatorPayLoad": {
                "status": 1
            }
        },
        {
            "operationType": 1,
            "micUpdatePayLoad": {
                "micMode": 1
            }
        }
    ],
    "projectName": "",
    "renderedHtml": "",
    "previewStartTimeMicros": "",
    "isEmptyResponse": false,
    "agentName": "daily bible",
    "servingModelOutdated": false,
    "request": "Talk to Daily Bible"
}