{
    "response": "Playing The Doctor who is making house calls online from MENA Report with Justin Murff, you can say older or newer to switch to a different episode.",
    "expectUserResponse": true,
    "conversationToken": "ErMDS2s1Vk...",
    "audioResponse": "//NExAAQmr...",
    "ssmlMarkList": [],
    "debugInfo": {
        "sharedDebugInfoList": [],
        "conversationBuilderExecutionEventsList": []
    },
    "conversationBuilderDebugInfo": {
        "eventList": []
    },
    "visualResponse": {
        "visualElementsList": [
            {
                "displayText": {
                    "content": "Playing The Doctor who is making house calls online from MENA Report with Justin Murff, you can say older or newer to switch to a different episode."
                }
            },
            {
                "simulatorMediaResponse": {
                    "mediaResponse": {
                        "mediaType": 1,
                        "mediaObjectsList": [
                            {
                                "name": "Playing The Doctor who is making house calls online from MENA Report with Justin Murff, you can say older or newer to switch to a different episode.",
                                "description": "Image from The MENA Report",
                                "largeImage": {
                                    "url": "https://content.swncdn.com/zcast/oneplace/host-images/the-mena-report/640x480.jpg?v=210203-547",
                                    "accessibilityText": "Image from The MENA Report",
                                    "height": 0,
                                    "width": 0
                                },
                                "contentUrl": "https://zcast.swncdn.com/episodes/zcast/the-mena-report/2021/05-17/885600/1524_2021423701.mp3"
                            }
                        ],
                        "startOffsetMs": 0,
                        "supportedMediaControlsList": [],
                        "repeatMode": 0,
                        "firstMediaObjectIndex": 0
                    },
                    "mediaSessionId": "-4709257078572378346"
                }
            }
        ],
        "suggestionsList": [
            {
                "title": "Older"
            },
            {
                "title": "Newer"
            }
        ],
        "agentLogoUrl": "https://lh3.googleusercontent.com/gIB7anBApLcBBT3Jhl1H4cAJBAUwtklnUGmcbJPjB0lBI5dl6kKFeSrjvNgNWEG4vk-oBNK-n4fH",
        "agentStyle": {
            "primaryColor": "",
            "fontFamily": "",
            "borderRadius": 0
        }
    },
    "clientError": 0,
    "is3pResponse": true,
    "clientOperationList": [
        {
            "operationType": 8,
            "showSuggestionsPayLoad": {
                "textsList": [
                    "Older",
                    "Newer"
                ]
            }
        }
    ],
    "projectName": "",
    "renderedHtml": "",
    "previewStartTimeMicros": "",
    "isEmptyResponse": false,
    "agentName": "Mena Report",
    "servingModelOutdated": false,
    "request": "play a random episode"
}