{
    "response": "I will play the sound of a bonfire.",
    "expectUserResponse": false,
    "conversationToken": "EosDS2o5Vk...",
    "audioResponse": "//NExAAQaJ...",
    "ssmlMarkList": [],
    "debugInfo": {
        "sharedDebugInfoList": [],
        "conversationBuilderExecutionEventsList": []
    },
    "conversationBuilderDebugInfo": {
        "eventList": []
    },
    "visualResponse": {
        "visualElementsList": [
            {
                "displayText": {
                    "content": "I will play the sound of a bonfire."
                }
            },
            {
                "simulatorMediaResponse": {
                    "mediaResponse": {
                        "mediaType": 1,
                        "mediaObjectsList": [
                            {
                                "name": "The sound of a bonfire.",
                                "description": "Sound effects obtained from https://www.freetousesounds.com",
                                "largeImage": {
                                    "url": "https://cdn.pixabay.com/photo/2016/11/18/17/02/bonfire-1835829_960_720.jpg",
                                    "accessibilityText": "bonfire image",
                                    "height": 0,
                                    "width": 0
                                },
                                "contentUrl": "https://sound-fetish.firebaseapp.com/bonfire-long.mp3"
                            }
                        ],
                        "startOffsetMs": 0,
                        "supportedMediaControlsList": [],
                        "repeatMode": 0,
                        "firstMediaObjectIndex": 0
                    },
                    "mediaSessionId": "-5035045885213328511"
                }
            }
        ],
        "suggestionsList": [],
        "agentLogoUrl": "https://lh3.googleusercontent.com/vcp639LOSan_4iGQQN9PGpGrEocoeASCzxlrXrU3_IoIe2-dfR0C1EXaNc7j4oDG8Yf6OfqqqgZ6",
        "agentStyle": {
            "primaryColor": "",
            "fontFamily": "",
            "borderRadius": 0
        }
    },
    "clientError": 0,
    "is3pResponse": true,
    "clientOperationList": [
        {
            "operationType": 4,
            "startIndicatorPayLoad": {
                "status": 1
            }
        },
        {
            "operationType": 7,
            "exitIndicatorPayLoad": {
                "status": 1
            }
        }
    ],
    "projectName": "",
    "renderedHtml": "",
    "previewStartTimeMicros": "",
    "isEmptyResponse": false,
    "agentName": "Sound of Bonfire",
    "servingModelOutdated": false,
    "request": "Talk to Sound of Bonfire"
}