{
    "response": "わかりました。 名言さんです。こんにちは。名言さんです。様々な方の名言を、200個ほど記憶しています。名言を聞きますか？",
    "expectUserResponse": true,
    "conversationToken": "EosDS2o5Uk...",
    "audioResponse": "//NExAAAAA...",
    "ssmlMarkList": [],
    "debugInfo": {
        "sharedDebugInfoList": [],
        "conversationBuilderExecutionEventsList": []
    },
    "conversationBuilderDebugInfo": {
        "eventList": []
    },
    "visualResponse": {
        "visualElementsList": [
            {
                "displayText": {
                    "content": "わかりました。名言さんです。"
                }
            },
            {
                "displayText": {
                    "content": "こんにちは。名言さんです。様々な方の名言を、200個ほど記憶しています。名言を聞きますか？"
                }
            }
        ],
        "suggestionsList": [],
        "agentLogoUrl": "https://lh3.googleusercontent.com/7UPmbXwFnQvNkPoVm6mLQon26DnFsW6o7ZsRWAY-Fbwo1CgU42soSfHaOg8WGItrrDmOkeYP34TF",
        "agentStyle": {
            "primaryColor": "",
            "fontFamily": "",
            "borderRadius": 0
        }
    },
    "clientError": 0,
    "is3pResponse": true,
    "clientOperationList": [
        {
            "operationType": 4,
            "startIndicatorPayLoad": {
                "status": 1
            }
        },
        {
            "operationType": 1,
            "micUpdatePayLoad": {
                "micMode": 1
            }
        }
    ],
    "projectName": "",
    "renderedHtml": "",
    "previewStartTimeMicros": "",
    "isEmptyResponse": false,
    "agentName": "名言さん",
    "servingModelOutdated": false,
    "request": "名言さんにつないで"
}