{
    "response": "すみません。聞き取れませんでした。",
    "expectUserResponse": true,
    "conversationToken": "ErMDS2s1dm...",
    "audioResponse": "//NExAAAAA...",
    "ssmlMarkList": [],
    "debugInfo": {
        "sharedDebugInfoList": [],
        "conversationBuilderExecutionEventsList": []
    },
    "conversationBuilderDebugInfo": {
        "eventList": []
    },
    "visualResponse": {
        "visualElementsList": [
            {
                "displayText": {
                    "content": "すみません。聞き取れませんでした。"
                }
            }
        ],
        "suggestionsList": [],
        "agentLogoUrl": "https://lh3.googleusercontent.com/IqcfliGeiRiYucB6vwnSAM-2Q7FniiXPOa2cEJnBFzh57mltLUGdv7RMLyCRRzYD8bUobTgOAn50wA",
        "agentStyle": {
            "primaryColor": "",
            "fontFamily": "",
            "borderRadius": 0
        }
    },
    "clientError": 0,
    "is3pResponse": true,
    "clientOperationList": [
        {
            "operationType": 1,
            "micUpdatePayLoad": {
                "micMode": 1
            }
        }
    ],
    "projectName": "",
    "renderedHtml": "",
    "previewStartTimeMicros": "",
    "isEmptyResponse": false,
    "agentName": "作業とりがー",
    "servingModelOutdated": false,
    "request": "はい"
}