{
    "response": "Alright. Getting Gujarat Facts.The Gujarati language is an Indo-Aryan language. The Gujarati language is part of the greater Indo-European language family. The Gujarati language is descended from the Sanskrit language.",
    "expectUserResponse": false,
    "conversationToken": "ErMDS2s1Rk...",
    "audioResponse": "//NExAAQ+D...",
    "ssmlMarkList": [],
    "debugInfo": {
        "sharedDebugInfoList": [],
        "conversationBuilderExecutionEventsList": []
    },
    "conversationBuilderDebugInfo": {
        "eventList": []
    },
    "visualResponse": {
        "visualElementsList": [
            {
                "displayText": {
                    "content": "Alright. Getting Gujarat Facts."
                }
            },
            {
                "displayText": {
                    "content": "The Gujarati language is an Indo-Aryan language. The Gujarati language is part of the greater Indo-European language family. The Gujarati language is descended from the Sanskrit language."
                }
            }
        ],
        "suggestionsList": [],
        "agentLogoUrl": "https://lh3.googleusercontent.com/g3KTbuZ7RBLS5RPvVfScKMBp8P_q4JMWCMkYgmVHLWO1QUETYRz1m7iK0OMpPJkO0CaRRKIp9AeIlg",
        "agentStyle": {
            "primaryColor": "",
            "fontFamily": "",
            "borderRadius": 16
        }
    },
    "clientError": 0,
    "is3pResponse": true,
    "clientOperationList": [
        {
            "operationType": 4,
            "startIndicatorPayLoad": {
                "status": 1
            }
        },
        {
            "operationType": 7,
            "exitIndicatorPayLoad": {
                "status": 1
            }
        }
    ],
    "projectName": "",
    "renderedHtml": "",
    "previewStartTimeMicros": "",
    "isEmptyResponse": false,
    "agentName": "Gujarat Facts",
    "servingModelOutdated": false,
    "request": "Ask Gujarat Facts about Gujarat facts"
}