{
    "response": "Quick tip: Apply hot oil and massage! Hot oil treatments are great for any hair type and are like a spa for your tresses. It help to strengthen and prevent dry, brittle hair and also split ends. It is also useful to stimulate blood flow, as well as helping with hair growth, preventing dandruff, dry scalp, frizziness, moisture and much more.\nWould you like to know random beauty hacks?",
    "expectUserResponse": true,
    "conversationToken": "EooES201bk...",
    "audioResponse": "//NExAASQE...",
    "ssmlMarkList": [],
    "debugInfo": {
        "sharedDebugInfoList": [],
        "conversationBuilderExecutionEventsList": []
    },
    "conversationBuilderDebugInfo": {
        "eventList": []
    },
    "visualResponse": {
        "visualElementsList": [
            {
                "displayText": {
                    "content": "Quick tip: Apply hot oil and massage! Hot oil treatments are great for any hair type and are like a spa for your tresses. It help to strengthen and prevent dry, brittle hair and also split ends. It is also useful to stimulate blood flow, as well as helping with hair growth, preventing dandruff, dry scalp, frizziness, moisture and much more.\nWould you like to know random beauty hacks?"
                }
            }
        ],
        "suggestionsList": [
            {
                "title": "Random Hack"
            },
            {
                "title": "Skin"
            },
            {
                "title": "Quit"
            }
        ],
        "agentLogoUrl": "https://lh3.googleusercontent.com/P3dX7ch05OIVlxm8YgHP3rc-H3qBasVMntDNI3gppxzoah8W9LomJESE5SuBiKXuJf1ZJCXfc62a",
        "agentStyle": {
            "primaryColor": "",
            "fontFamily": "",
            "borderRadius": 0
        }
    },
    "clientError": 0,
    "is3pResponse": true,
    "clientOperationList": [
        {
            "operationType": 8,
            "showSuggestionsPayLoad": {
                "textsList": [
                    "Random Hack",
                    "Skin",
                    "Quit"
                ]
            }
        },
        {
            "operationType": 1,
            "micUpdatePayLoad": {
                "micMode": 1
            }
        }
    ],
    "projectName": "",
    "renderedHtml": "",
    "previewStartTimeMicros": "",
    "isEmptyResponse": false,
    "agentName": "Beauty Companion",
    "servingModelOutdated": false,
    "request": "Male"
}