{
    "response": "Hello User, welcome to LUCKY COLOR DSC. This action will give you your lucky number. what is your favorite color ?",
    "expectUserResponse": true,
    "conversationToken": "ErMDS2s1Rk...",
    "audioResponse": "//NExAAQaJ...",
    "ssmlMarkList": [],
    "debugInfo": {
        "sharedDebugInfoList": [],
        "conversationBuilderExecutionEventsList": []
    },
    "conversationBuilderDebugInfo": {
        "eventList": []
    },
    "visualResponse": {
        "visualElementsList": [
            {
                "displayText": {
                    "content": "Hello User, welcome to LUCKY COLOR DSC. This action will give you your lucky number. what is your favorite color ?"
                }
            }
        ],
        "suggestionsList": [],
        "agentLogoUrl": "https://lh3.googleusercontent.com/9UQoAN-lZtMPZ5XV4ogJiUOj_R1H7Rtrv7yL5EpAK48ouQ9ykqqHBaelAjVUMcsS6jrbo781mx9H",
        "agentStyle": {
            "primaryColor": "",
            "fontFamily": "",
            "borderRadius": 0
        }
    },
    "clientError": 0,
    "is3pResponse": true,
    "clientOperationList": [
        {
            "operationType": 4,
            "startIndicatorPayLoad": {
                "status": 1
            }
        },
        {
            "operationType": 1,
            "micUpdatePayLoad": {
                "micMode": 1
            }
        }
    ],
    "projectName": "",
    "renderedHtml": "",
    "previewStartTimeMicros": "",
    "isEmptyResponse": false,
    "agentName": "lucky number dsc",
    "servingModelOutdated": false,
    "request": "Talk to lucky number dsc"
}