{
    "2": {
        "req": "CKDオンラインにつないで",
        "res": "はい。 CKDオンラインです。ご質問をどうぞ。",
        "QType": "START",
        "Q_id": 1,
        "over": false,
        "canvas": false,
        "id": 2,
        "req_list": [
            "CKDオンラインにつないで"
        ],
        "candidates": {
            "NE": {},
            "EXAMPLE": {
                "1": {
                    "req": "クレアチニンクリアランス48の時の、サワシリンの投与量教えて",
                    "visit": true,
                    "child": [
                        3
                    ],
                    "loop_start": false,
                    "loop_end": [],
                    "loop_count": 1
                },
                "2": {
                    "req": "透析の時の、ユナシンの投与量教えて",
                    "visit": true,
                    "child": [
                        4
                    ],
                    "loop_start": false,
                    "loop_end": [],
                    "loop_count": 1
                }
            },
            "OTHER": {
                "1": {
                    "req": "オンラインを教えてください",
                    "visit": true,
                    "child": [
                        5
                    ],
                    "loop_start": false,
                    "loop_end": [],
                    "loop_count": 1
                },
                "2": {
                    "req": "腎機能を教えてください",
                    "visit": false,
                    "child": [],
                    "loop_start": false,
                    "loop_end": [],
                    "loop_count": 1
                },
                "3": {
                    "req": "薬を教えてください",
                    "visit": false,
                    "child": [],
                    "loop_start": false,
                    "loop_end": [],
                    "loop_count": 1
                },
                "4": {
                    "req": "量を教えてください",
                    "visit": false,
                    "child": [],
                    "loop_start": false,
                    "loop_end": [],
                    "loop_count": 1
                },
                "5": {
                    "req": "クレアチニンを教えてください",
                    "visit": false,
                    "child": [],
                    "loop_start": false,
                    "loop_end": [],
                    "loop_count": 1
                },
                "6": {
                    "req": "クリアランスを教えてください",
                    "visit": false,
                    "child": [],
                    "loop_start": false,
                    "loop_end": [],
                    "loop_count": 1
                },
                "7": {
                    "req": "サワシリンを教えてください",
                    "visit": false,
                    "child": [],
                    "loop_start": false,
                    "loop_end": [],
                    "loop_count": 1
                },
                "8": {
                    "req": "ユナシンを教えてください",
                    "visit": false,
                    "child": [],
                    "loop_start": false,
                    "loop_end": [],
                    "loop_count": 1
                },
                "9": {
                    "req": "事項を教えてください",
                    "visit": false,
                    "child": [],
                    "loop_start": false,
                    "loop_end": [],
                    "loop_count": 1
                },
                "10": {
                    "req": "アプリを教えてください",
                    "visit": false,
                    "child": [],
                    "loop_start": false,
                    "loop_end": [],
                    "loop_count": 1
                },
                "11": {
                    "req": "情報を教えてください",
                    "visit": false,
                    "child": [],
                    "loop_start": false,
                    "loop_end": [],
                    "loop_count": 1
                },
                "12": {
                    "req": "医師を教えてください",
                    "visit": false,
                    "child": [],
                    "loop_start": false,
                    "loop_end": [],
                    "loop_count": 1
                },
                "13": {
                    "req": "薬剤を教えてください",
                    "visit": false,
                    "child": [],
                    "loop_start": false,
                    "loop_end": [],
                    "loop_count": 1
                },
                "14": {
                    "req": "師を教えてください",
                    "visit": false,
                    "child": [],
                    "loop_start": false,
                    "loop_end": [],
                    "loop_count": 1
                },
                "15": {
                    "req": "専門を教えてください",
                    "visit": false,
                    "child": [],
                    "loop_start": false,
                    "loop_end": [],
                    "loop_count": 1
                },
                "16": {
                    "req": "患者を教えてください",
                    "visit": false,
                    "child": [],
                    "loop_start": false,
                    "loop_end": [],
                    "loop_count": 1
                }
            }
        },
        "parent": 1
    }
}