{
    "response": "OK. Getting I T fundamentals for Students.Welcome to IT Fundamentals for Students: Introduces computer hardware, computer software, databases, networking, security, and software development. This course comprises 15 lessons covering IT fundamentals. ... The course also assists learners in preparing for CompTIA IT Fundamentals certification.",
    "expectUserResponse": true,
    "conversationToken": "EosDS2o5Vk...",
    "audioResponse": "//NExAARgD...",
    "ssmlMarkList": [],
    "debugInfo": {
        "sharedDebugInfoList": [],
        "conversationBuilderExecutionEventsList": []
    },
    "conversationBuilderDebugInfo": {
        "eventList": []
    },
    "visualResponse": {
        "visualElementsList": [
            {
                "displayText": {
                    "content": "OK. Getting I T fundamentals for Students."
                }
            },
            {
                "displayText": {
                    "content": "Welcome to IT Fundamentals for Students: Introduces computer hardware, computer software, databases, networking, security, and software development. This course comprises 15 lessons covering IT fundamentals. ... The course also assists learners in preparing for CompTIA IT Fundamentals certification."
                }
            }
        ],
        "suggestionsList": [
            {
                "title": "Computer Hardware"
            },
            {
                "title": "Computer Software"
            },
            {
                "title": "Exit"
            }
        ],
        "agentLogoUrl": "https://lh3.googleusercontent.com/oRRW2ujag757JhB51A97mGT-xFp0k4iN8pLk5yQcAJIMShUtBv4C9vu-Aaw5icY7F9r_N1zw2r8L",
        "agentStyle": {
            "primaryColor": "",
            "fontFamily": "",
            "borderRadius": 0
        }
    },
    "clientError": 0,
    "is3pResponse": true,
    "clientOperationList": [
        {
            "operationType": 4,
            "startIndicatorPayLoad": {
                "status": 1
            }
        },
        {
            "operationType": 8,
            "showSuggestionsPayLoad": {
                "textsList": [
                    "Computer Hardware",
                    "Computer Software",
                    "Exit"
                ]
            }
        },
        {
            "operationType": 1,
            "micUpdatePayLoad": {
                "micMode": 1
            }
        }
    ],
    "projectName": "",
    "renderedHtml": "",
    "previewStartTimeMicros": "",
    "isEmptyResponse": false,
    "agentName": "I T fundamentals for Students",
    "servingModelOutdated": false,
    "request": "Talk to I T fundamentals for Students"
}