{
    "43": {
        "req": "Easy",
        "res": "Let's play easy level",
        "QType": "OPTION",
        "Q_id": 1,
        "over": false,
        "canvas": false,
        "id": 43,
        "req_list": [
            "Easy"
        ],
        "candidates": {
            "OPTION": {
                "1": {
                    "req": "Ready to play easy level?",
                    "visit": false,
                    "child": [
                        44
                    ],
                    "loop_start": false,
                    "loop_end": [],
                    "loop_count": 1
                }
            },
            "OTHER": {
                "1": {
                    "req": "I want to know Trivia Challenge.",
                    "visit": false,
                    "child": [],
                    "loop_start": false,
                    "loop_end": [],
                    "loop_count": 1
                },
                "2": {
                    "req": "I want to know Spanish.",
                    "visit": false,
                    "child": [],
                    "loop_start": false,
                    "loop_end": [],
                    "loop_count": 1
                },
                "3": {
                    "req": "I want to know La Casa De Papel.",
                    "visit": false,
                    "child": [],
                    "loop_start": false,
                    "loop_end": [],
                    "loop_count": 1
                },
                "4": {
                    "req": "I want to know English: Money Heist.",
                    "visit": false,
                    "child": [],
                    "loop_start": false,
                    "loop_end": [],
                    "loop_count": 1
                },
                "5": {
                    "req": "I want to know Season 1 to Season.",
                    "visit": false,
                    "child": [],
                    "loop_start": false,
                    "loop_end": [],
                    "loop_count": 1
                }
            }
        },
        "parent": 42
    }
}