{
    "response": "OK Jackson , Now ask me, Mirror Mirror who is the... of all .",
    "expectUserResponse": true,
    "conversationToken": "EosDS2o5bk...",
    "audioResponse": "//NExAAR0E...",
    "ssmlMarkList": [],
    "debugInfo": {
        "sharedDebugInfoList": [],
        "conversationBuilderExecutionEventsList": []
    },
    "conversationBuilderDebugInfo": {
        "eventList": []
    },
    "visualResponse": {
        "visualElementsList": [
            {
                "displayText": {
                    "content": "OK Jackson , Now ask me, Mirror Mirror who is the...  of all ."
                }
            }
        ],
        "suggestionsList": [],
        "agentLogoUrl": "https://lh3.googleusercontent.com/TdFS8gkk7IDJ44eLWSl6xtRRWVuuiODu6u0b4aYJpTzFgoRn1bp6j4LiaGsciooKfkykfnt6z_8bbw",
        "agentStyle": {
            "primaryColor": "#101010",
            "fontFamily": "cursive",
            "borderRadius": 16,
            "backgroundColor": "#fafafa"
        }
    },
    "clientError": 0,
    "is3pResponse": true,
    "clientOperationList": [
        {
            "operationType": 1,
            "micUpdatePayLoad": {
                "micMode": 1
            }
        }
    ],
    "projectName": "",
    "renderedHtml": "",
    "previewStartTimeMicros": "",
    "isEmptyResponse": false,
    "agentName": "Enchanting Mirror",
    "servingModelOutdated": false,
    "request": "Jackson"
}