{
    "response": "Before we get started, would you like to hear your daily dose of good news or todays quote of motivation and inspiration?",
    "expectUserResponse": true,
    "conversationToken": "EosDS2o5ek...",
    "audioResponse": "//NExAARsA...",
    "ssmlMarkList": [],
    "debugInfo": {
        "sharedDebugInfoList": [],
        "conversationBuilderExecutionEventsList": []
    },
    "conversationBuilderDebugInfo": {
        "eventList": []
    },
    "visualResponse": {
        "visualElementsList": [
            {
                "displayText": {
                    "content": "Before we get started, would you like to hear your daily dose of good news or todays quote of motivation and inspiration?"
                }
            }
        ],
        "suggestionsList": [],
        "agentLogoUrl": "https://lh3.googleusercontent.com/-d_1PptZ76aJuAI4D6yYiyoCMpdKomTcvtIQsu1D95KBYt63JnjewvtLMxsyBmIhYUAWg3vRIxI",
        "agentStyle": {
            "primaryColor": "",
            "fontFamily": "",
            "borderRadius": 0
        }
    },
    "clientError": 0,
    "is3pResponse": true,
    "clientOperationList": [
        {
            "operationType": 1,
            "micUpdatePayLoad": {
                "micMode": 1
            }
        }
    ],
    "projectName": "",
    "renderedHtml": "",
    "previewStartTimeMicros": "",
    "isEmptyResponse": false,
    "agentName": "glass half full",
    "servingModelOutdated": false,
    "request": "Yes"
}