{
    "response": "わかりました。 動物の漢字です。こんにちは！動物の名前を言ってください。",
    "expectUserResponse": true,
    "conversationToken": "EosDS2o5Uk...",
    "audioResponse": "//NExAAAAA...",
    "ssmlMarkList": [],
    "debugInfo": {
        "sharedDebugInfoList": [],
        "conversationBuilderExecutionEventsList": []
    },
    "conversationBuilderDebugInfo": {
        "eventList": []
    },
    "visualResponse": {
        "visualElementsList": [
            {
                "displayText": {
                    "content": "わかりました。動物の漢字です。"
                }
            },
            {
                "displayText": {
                    "content": "こんにちは！動物の名前を言ってください。"
                }
            }
        ],
        "suggestionsList": [],
        "agentLogoUrl": "https://lh3.googleusercontent.com/5chVeis4lH0CTvWTGyOZzOeBSuRZ1tTElKvkWIyhRxUW2qEvdKUyMFezj36C81F6dKxXnufgt_uPqw",
        "agentStyle": {
            "primaryColor": "",
            "fontFamily": "",
            "borderRadius": 0
        }
    },
    "clientError": 0,
    "is3pResponse": true,
    "clientOperationList": [
        {
            "operationType": 4,
            "startIndicatorPayLoad": {
                "status": 1
            }
        },
        {
            "operationType": 1,
            "micUpdatePayLoad": {
                "micMode": 1
            }
        }
    ],
    "projectName": "",
    "renderedHtml": "",
    "previewStartTimeMicros": "",
    "isEmptyResponse": false,
    "agentName": "動物の漢字",
    "servingModelOutdated": false,
    "request": "動物の漢字につないで"
}