{
    "response": "Alright. Let's get Bridlington Gold.You are now listening to Bridlington Gold.",
    "expectUserResponse": false,
    "conversationToken": "EosDS2o5Vk...",
    "audioResponse": "//NExAAQ+D...",
    "ssmlMarkList": [],
    "debugInfo": {
        "sharedDebugInfoList": [],
        "conversationBuilderExecutionEventsList": []
    },
    "conversationBuilderDebugInfo": {
        "eventList": []
    },
    "visualResponse": {
        "visualElementsList": [
            {
                "displayText": {
                    "content": "Alright. Let's get Bridlington Gold."
                }
            },
            {
                "displayText": {
                    "content": "You are now listening to Bridlington Gold. "
                }
            },
            {
                "simulatorMediaResponse": {
                    "mediaResponse": {
                        "mediaType": 1,
                        "mediaObjectsList": [
                            {
                                "name": "Bridlington Gold",
                                "description": "The Music you Love",
                                "largeImage": {
                                    "url": "https://s3.amazonaws.com/com.getstoryflow.api.images/1607617266552-brid-gold-square-logo.png",
                                    "accessibilityText": "Media Background Image",
                                    "height": 0,
                                    "width": 0
                                },
                                "contentUrl": "https://bridgold.radioca.st/stream"
                            }
                        ],
                        "startOffsetMs": 0,
                        "supportedMediaControlsList": [
                            3,
                            4
                        ],
                        "repeatMode": 0,
                        "firstMediaObjectIndex": 0
                    },
                    "mediaSessionId": "5411448882392972203"
                }
            }
        ],
        "suggestionsList": [],
        "agentLogoUrl": "https://lh3.googleusercontent.com/1V7Lsqq2p-5JJrFvMXosAx5qPFETBeDslLyrRbaD9sIdCbPMmg36AaKwudDkSN5zcML-7C2S-8M",
        "agentStyle": {
            "primaryColor": "",
            "fontFamily": "",
            "borderRadius": 0
        }
    },
    "clientError": 0,
    "is3pResponse": true,
    "clientOperationList": [
        {
            "operationType": 4,
            "startIndicatorPayLoad": {
                "status": 1
            }
        },
        {
            "operationType": 7,
            "exitIndicatorPayLoad": {
                "status": 1
            }
        }
    ],
    "projectName": "",
    "renderedHtml": "",
    "previewStartTimeMicros": "",
    "isEmptyResponse": false,
    "agentName": "Bridlington Gold",
    "servingModelOutdated": false,
    "request": "Talk to Bridlington Gold"
}